{"name":"beach-party-arainn-mhor","album":"people","public_id":"people/beach-party-arainn-mhor","format":"tiff","version":1520779690,"created_at":"2018-03-11T14:48:10Z","width":2560,"height":1440,"tags":[],"colors":[{"code":"#7B514F","weight":18.6},{"code":"#E4DEDA","weight":16.3},{"code":"#382120","weight":14.3},{"code":"#485879","weight":11.6},{"code":"#191E2B","weight":7.5},{"code":"#282322","weight":3.6},{"code":"#26040A","weight":3.5},{"code":"#7A5A4F","weight":3},{"code":"#252329","weight":2.2},{"code":"#6C6D81","weight":1.9},{"code":"#756865","weight":1.6},{"code":"#3C3723","weight":1.6},{"code":"#020309","weight":1.4},{"code":"#363B1D","weight":1.3},{"code":"#A5A9C0","weight":1.2},{"code":"#7D8FB7","weight":1.2},{"code":"#680F22","weight":0.9},{"code":"#032B1B","weight":0.9},{"code":"#140C11","weight":0.7},{"code":"#F1F1F0","weight":0.6},{"code":"#B57B75","weight":0.6},{"code":"#121C22","weight":0.6}],"image_metadata":{"ApplicationRecordVersion":"0","DateCreated":"2010:06:07","TimeCreated":"05:47:23+00:00","SubfileType":"Full-resolution Image","ImageWidth":"2560","ImageHeight":"1440","BitsPerSample":"8 8 8","Compression":"LZW","PhotometricInterpretation":"RGB","Make":"NIKON CORPORATION","Model":"NIKON D200","Orientation":"Horizontal (normal)","SamplesPerPixel":"3","RowsPerStrip":"34","XResolution":"300","YResolution":"300","PlanarConfiguration":"Chunky","ResolutionUnit":"inches","Software":"Adobe Photoshop CC (Macintosh)","ModifyDate":"2018:03:11 15:47:24","Predictor":"Horizontal differencing","ExposureTime":"1/400","FNumber":"3.8","ExposureProgram":"Manual","ISO":"800","ExifVersion":"0221","DateTimeOriginal":"2010:06:07 05:47:23","CreateDate":"2010:06:07 05:47:23","ShutterSpeedValue":"1/400","ApertureValue":"3.8","ExposureCompensation":"-1/3","MaxApertureValue":"3.9","MeteringMode":"Spot","LightSource":"Unknown","Flash":"No Flash","FocalLength":"24.0 mm","SubSecTime":"65","SubSecTimeOriginal":"65","SubSecTimeDigitized":"65","ColorSpace":"Uncalibrated","ExifImageWidth":"2560","ExifImageHeight":"1440","SensingMethod":"One-chip color area","FileSource":"Digital Camera","SceneType":"Directly photographed","CFAPattern":"[Green,Red][Blue,Green]","CustomRendered":"Normal","ExposureMode":"Manual","DigitalZoomRatio":"1","FocalLengthIn35mmFormat":"36 mm","SceneCaptureType":"Standard","GainControl":"Low gain up","Contrast":"High","Saturation":"High","Sharpness":"Hard","SubjectDistanceRange":"Unknown","LensInfo":"18-55mm f/3.5-5.6","LensModel":"18.0-55.0 mm f/3.5-5.6","XMPToolkit":"Adobe XMP Core 5.6-c140 79.160451, 2017/05/06-01:08:21","CreatorTool":"Ver.1.00","Rating":"0","MetadataDate":"2018:03:11 15:47:24+01:00","Lens":"18.0-55.0 mm f/3.5-5.6","LensID":"140","ImageNumber":"26193","ApproximateFocusDistance":"2.11","ColorMode":"RGB","ICCProfileName":"Adobe RGB (1998)","DocumentID":"adobe:docid:photoshop:1318632b-5be9-6446-b921-9b2e2c0d56af","HistoryAction":"derived, saved, saved","HistoryParameters":"converted from image/x-nikon-nef to image/tiff","HistoryInstanceID":"xmp.iid:f5c4227b-5320-4e35-9320-332efbfe2990, xmp.iid:be1dd1bb-6e08-4d31-9876-a9c50ff88b29","HistoryWhen":"2018:03:11 15:45:34+01:00, 2018:03:11 15:47:24+01:00","HistorySoftwareAgent":"Adobe Photoshop Camera Raw 10.2 (Macintosh), Adobe Photoshop CC (Macintosh)","HistoryChanged":"/, /","OriginalDocumentID":"CE9D51A11EB0735B1A08E961E59B2DD0","DerivedFromDocumentID":"CE9D51A11EB0735B1A08E961E59B2DD0","DerivedFromOriginalDocumentID":"CE9D51A11EB0735B1A08E961E59B2DD0","InstanceID":"xmp.iid:be1dd1bb-6e08-4d31-9876-a9c50ff88b29","Format":"image/tiff","RawFileName":"_DSC6058.NEF","Version":"10.2","ProcessVersion":"10.0","WhiteBalance":"As Shot","ColorTemperature":"6850","Tint":"+2","LuminanceSmoothing":"0","ColorNoiseReduction":"25","VignetteAmount":"0","ShadowTint":"0","RedHue":"0","RedSaturation":"0","GreenHue":"0","GreenSaturation":"0","BlueHue":"0","BlueSaturation":"0","Vibrance":"+20","HueAdjustmentRed":"0","HueAdjustmentOrange":"0","HueAdjustmentYellow":"0","HueAdjustmentGreen":"0","HueAdjustmentAqua":"0","HueAdjustmentBlue":"0","HueAdjustmentPurple":"0","HueAdjustmentMagenta":"0","SaturationAdjustmentRed":"0","SaturationAdjustmentOrange":"0","SaturationAdjustmentYellow":"0","SaturationAdjustmentGreen":"0","SaturationAdjustmentAqua":"0","SaturationAdjustmentBlue":"0","SaturationAdjustmentPurple":"0","SaturationAdjustmentMagenta":"0","LuminanceAdjustmentRed":"0","LuminanceAdjustmentOrange":"0","LuminanceAdjustmentYellow":"0","LuminanceAdjustmentGreen":"0","LuminanceAdjustmentAqua":"0","LuminanceAdjustmentBlue":"0","LuminanceAdjustmentPurple":"0","LuminanceAdjustmentMagenta":"0","SplitToningShadowHue":"0","SplitToningShadowSaturation":"0","SplitToningHighlightHue":"0","SplitToningHighlightSaturation":"0","SplitToningBalance":"0","ParametricShadows":"0","ParametricDarks":"0","ParametricLights":"0","ParametricHighlights":"0","ParametricShadowSplit":"25","ParametricMidtoneSplit":"50","ParametricHighlightSplit":"75","SharpenRadius":"+1.0","SharpenDetail":"25","SharpenEdgeMasking":"0","PostCropVignetteAmount":"0","GrainAmount":"0","ColorNoiseReductionDetail":"50","ColorNoiseReductionSmoothness":"50","LensProfileEnable":"0","LensManualDistortionAmount":"0","PerspectiveVertical":"0","PerspectiveHorizontal":"0","PerspectiveRotate":"0.0","PerspectiveScale":"100","PerspectiveAspect":"0","PerspectiveUpright":"0","PerspectiveX":"0.0","PerspectiveY":"0.0","AutoLateralCA":"0","Exposure2012":"+0.20","Contrast2012":"+21","Highlights2012":"-70","Shadows2012":"+5","Whites2012":"-50","Blacks2012":"-10","Clarity2012":"+27","DefringePurpleAmount":"0","DefringePurpleHueLo":"30","DefringePurpleHueHi":"70","DefringeGreenAmount":"0","DefringeGreenHueLo":"40","DefringeGreenHueHi":"60","Dehaze":"0","ConvertToGrayscale":"false","ToneCurveName":"Medium Contrast","ToneCurve":"0, 0, 32, 22, 64, 56, 128, 128, 192, 196, 255, 255","ToneCurveRed":"0, 0, 255, 255","ToneCurveGreen":"0, 0, 255, 255","ToneCurveBlue":"0, 0, 255, 255","ToneCurveName2012":"Linear","ToneCurvePV2012":"0, 0, 255, 255","ToneCurvePV2012Red":"0, 0, 255, 255","ToneCurvePV2012Green":"0, 0, 255, 255","ToneCurvePV2012Blue":"0, 0, 255, 255","CameraProfile":"Adobe Standard","CameraProfileDigest":"EEAE3DBFE03C629F248FDD41FFC507B5","LensProfileSetup":"LensDefaults","UprightVersion":"151388160","UprightCenterMode":"0","UprightCenterNormX":"0.5","UprightCenterNormY":"0.5","UprightFocalMode":"0","UprightFocalLength35mm":"35","UprightPreview":"false","UprightTransformCount":"6","UprightFourSegmentsCount":"0","HasSettings":"true","HasCrop":"false","AlreadyApplied":"true","IPTCDigest":"e06ed554000fbff886965859bacf8d02","DisplayedUnitsX":"inches","DisplayedUnitsY":"inches","PrintStyle":"Centered","PrintPosition":"0 0","PrintScale":"1","GlobalAngle":"30","GlobalAltitude":"30","URL_List":"","SlicesGroupName":"","NumSlices":"1","PixelAspectRatio":"1","HasRealMergedData":"Yes","WriterName":"Adobe Photoshop","ReaderName":"Adobe Photoshop CC","ProfileDescription":"Adobe RGB (1998)","Colorspace":"RGB","DPI":"300"}}